rustkissvdb/__init__.py
rustkissvdb/client.py
rustkissvdb/config.py
rustkissvdb/doc.py
rustkissvdb/errors.py
rustkissvdb/sql.py
rustkissvdb/state.py
rustkissvdb/stream.py
rustkissvdb/vector.py
rustkissvdb-0.1.1.dist-info/METADATA
rustkissvdb-0.1.1.dist-info/WHEEL
rustkissvdb-0.1.1.dist-info/top_level.txt
rustkissvdb-0.1.1.dist-info/RECORD
