Metadata-Version: 2.4
Name: rustkissvdb
Version: 0.1.1
Summary: SDK Python para RustKissVDB (state, vector, docstore, sql y stream).
Requires-Python: >=3.11
Requires-Dist: httpx>=0.28.1
Requires-Dist: python-dotenv>=1.0.0
Provides-Extra: rag
Requires-Dist: pymupdf>=1.26.7; extra == "rag"
